metaDMG/PMD.py
metaDMG/__init__.py
metaDMG/__main__.py
metaDMG/__version__.py
metaDMG/cli/__init__.py
metaDMG/cli/cli.py
metaDMG/cli/cli_gui.py
metaDMG/cli/cli_utils.py
metaDMG/data/__init__.py
metaDMG/data/acc2taxid.map.gz
metaDMG/data/alignment.sorted.bam
metaDMG/data/data.py
metaDMG/data/names-mdmg.dmp
metaDMG/data/nodes-mdmg.dmp
metaDMG/errors.py
metaDMG/filters.py
metaDMG/fit/__init__.py
metaDMG/fit/bayesian.py
metaDMG/fit/fit_utils.py
metaDMG/fit/fits.py
metaDMG/fit/frequentist.py
metaDMG/fit/mismatch_to_mapDamage.py
metaDMG/fit/mismatches.py
metaDMG/fit/results.py
metaDMG/fit/serial.py
metaDMG/fit/workflow.py
metaDMG/loggers/__init__.py
metaDMG/loggers/log_config.yaml
metaDMG/loggers/loggers.py
metaDMG/main.py
metaDMG/utils.py
metaDMG/viz/__init__.py
metaDMG/viz/_taxonomy.py
metaDMG/viz/app.py
metaDMG/viz/content.py
metaDMG/viz/dashboard.py
metaDMG/viz/figures.py
metaDMG/viz/mpl_styles/__init__.py
metaDMG/viz/mpl_styles/ieee.mplstyle
metaDMG/viz/mpl_styles/no-latex.mplstyle
metaDMG/viz/mpl_styles/scatter.mplstyle
metaDMG/viz/mpl_styles/science.mplstyle
metaDMG/viz/results.py
metaDMG/viz/viz_utils.py
metadmg-0.38.0.dist-info/entry_points.txt
metadmg-0.38.0.dist-info/METADATA
metadmg-0.38.0.dist-info/LICENSE
metadmg-0.38.0.dist-info/WHEEL
metadmg-0.38.0.dist-info/RECORD
