Metadata-Version: 2.1
Name: metadmg
Version: 0.38.0
Summary: metaDMG: Estimating ancient damage in (meta)genomic DNA rapidly
Home-page: https://github.com/metaDMG/metaDMG/
License: MIT
Author: Christian Michelsen
Author-email: christianmichelsen@gmail.com
Requires-Python: >=3.9,<3.11
Classifier: License :: OSI Approved :: MIT License
Classifier: Programming Language :: Python :: 3
Classifier: Programming Language :: Python :: 3.9
Classifier: Programming Language :: Python :: 3.10
Provides-Extra: all
Provides-Extra: fit
Provides-Extra: gui
Provides-Extra: viz
Requires-Dist: PyYAML (>=6.0,<7.0)
Requires-Dist: customtkinter (>=4.6.3,<5.0.0) ; extra == "gui" or extra == "all"
Requires-Dist: dash-bootstrap-components (>=1.2.1,<2.0.0) ; extra == "viz" or extra == "all"
Requires-Dist: dash[diskcache] (>=2.6.2,<3.0.0) ; extra == "viz" or extra == "all"
Requires-Dist: flatbuffers (>=22.9.24,<23.0.0) ; extra == "fit" or extra == "all"
Requires-Dist: iminuit (>=2.17.0,<3.0.0) ; extra == "fit" or extra == "all"
Requires-Dist: joblib (>=1.2.0,<2.0.0) ; extra == "fit" or extra == "all"
Requires-Dist: logger-tt (>=1.7.0,<2.0.0) ; extra == "fit" or extra == "all"
Requires-Dist: matplotlib (>=3.6.0,<4.0.0) ; extra == "viz" or extra == "all"
Requires-Dist: natsort (>=8.2.0,<9.0.0)
Requires-Dist: numba (>=0.56.2,<0.57.0) ; extra == "fit" or extra == "all"
Requires-Dist: numpyro (>=0.10.1,<0.11.0) ; extra == "fit" or extra == "all"
Requires-Dist: orjson (>=3.8.0,<4.0.0) ; extra == "viz" or extra == "all"
Requires-Dist: pandas (>=1.5.0,<2.0.0)
Requires-Dist: plotly (>=5.10.0,<6.0.0) ; extra == "viz" or extra == "all"
Requires-Dist: psutil (>=5.9.2,<6.0.0) ; extra == "fit" or extra == "all"
Requires-Dist: pyarrow (>=9.0.0,<10.0.0)
Requires-Dist: scipy (>=1.9.1,<2.0.0)
Requires-Dist: tqdm (>=4.64.1,<5.0.0) ; extra == "viz" or extra == "all"
Requires-Dist: typer[all] (>=0.6.1,<0.7.0)
Project-URL: Repository, https://github.com/metaDMG/metaDMG/
